{
  "$schema": "http://json-schema.org/draft-07/schema#",
  "$id": "docs/contracts/CSLT-02/TagFilterDto.json",
  "title": "TagFilterDto",
  "description": "档案标签过滤条件的数据传输对象。由上游PROF-02从患者个性化档案中提取并标准化后传入。CSLT-02临时自包含定义此类型，待PROF-02契约落地后改为引用PROF-02的标准契约。",
  "type": "object",
  "x-defined-by": "CSLT-02",
  "x-consumers": [],
  "x-maturity": "draft",
  "x-contract-type": "shared-model",
  "x-version": "1.0.0",
  "properties": {
    "age_range": {
      "type": "string",
      "description": "患者年龄段。枚举值由PROF-02定义（如：学龄前(0-5岁)、学龄儿童(6-12岁)、青少年(13-18岁)、成年人(19+岁)）。本模块仅消费过滤，不定义枚举取值范围。",
      "minLength": 1,
      "examples": ["学龄儿童(6-12岁)"]
    },
    "behavior_type": {
      "type": "string",
      "description": "主要行为类型。枚举值引用CSLT-01/BehaviorTypeCategory契约。取值：SELF_INJURY、AGGRESSION、ELOPEMENT、MEDICATION、EMOTIONAL_MELTDOWN、STEREOTYPY、OTHER",
      "enum": ["SELF_INJURY", "AGGRESSION", "ELOPEMENT", "MEDICATION", "EMOTIONAL_MELTDOWN", "STEREOTYPY", "OTHER"],
      "examples": ["EMOTIONAL_MELTDOWN"]
    },
    "emotion_level": {
      "type": "string",
      "description": "情绪等级（可选）。用于精确过滤。枚举值：轻、中、重。为null时不应用此过滤条件。",
      "enum": ["轻", "中", "重"],
      "examples": ["重"]
    },
    "sensory_features": {
      "type": "string",
      "description": "感官特征标签（可选）。如听觉敏感、触觉敏感、视觉敏感等。为null时不应用此过滤条件。",
      "examples": ["听觉敏感"]
    }
  },
  "required": ["age_range", "behavior_type"],
  "additionalProperties": false
}
